bolt/__init__.py
bolt/_btapp.py
bolt/_btconfig.py
bolt/_btoptions.py
bolt/_btregistry.py
bolt/_btrunner.py
bolt/_btutils.py
bolt/api.py
bolt/errors.py
bolt/project.py
bolt/tasks/__init__.py
bolt/tasks/bolt_conttest.py
bolt/tasks/bolt_coverage.py
bolt/tasks/bolt_delete_files.py
bolt/tasks/bolt_mkdir.py
bolt/tasks/bolt_nose.py
bolt/tasks/bolt_pip.py
bolt/tasks/bolt_set_vars.py
bolt/tasks/bolt_setup.py
bolt/tasks/bolt_shell.py
bolt/tasks/bolt_sleep.py
bolt/utils/__init__.py
bolt/utils/_utconfig.py
bolt/utils/_utfiles.py
bolt/utils/_uttime.py
bolt/utils/log.py
bolt_ta-0.4.1.dist-info/METADATA
bolt_ta-0.4.1.dist-info/WHEEL
bolt_ta-0.4.1.dist-info/entry_points.txt
bolt_ta-0.4.1.dist-info/licenses/LICENSE
bolt_ta-0.4.1.dist-info/RECORD
