Metadata-Version: 2.4
Name: bolt-ta
Version: 0.4.1
Summary: A simple task runner written in Python
Project-URL: Homepage, https://github.com/abantos/bolt
Project-URL: Documentation, https://bolt-task-automation.readthedocs.io/en/latest/
Project-URL: Repository, https://github.com/abantos/bolt
Author-email: Abantos <oss.abantos@outlook.com>
License-Expression: MIT
License-File: LICENSE
Classifier: Development Status :: 4 - Beta
Classifier: Environment :: Console
Classifier: Intended Audience :: Developers
Classifier: License :: OSI Approved :: MIT License
Classifier: Programming Language :: Python
Classifier: Programming Language :: Python :: 3.8
Classifier: Programming Language :: Python :: 3.9
Classifier: Programming Language :: Python :: 3.10
Classifier: Programming Language :: Python :: 3.11
Classifier: Programming Language :: Python :: 3.12
Classifier: Topic :: Software Development :: Build Tools
Classifier: Topic :: Utilities
Requires-Python: >=3.8
Requires-Dist: docutils<0.21
